{"cameraMode":{"drawMode":0,"name":"Shaded","section":"Shading Mode"},"sceneLighting":false,"audioPlay":false,"sceneViewState":{"m_AlwaysRefresh":false,"showFog":true,"showSkybox":false,"showFlares":true,"showImageEffects":true,"showParticleSystems":true,"showVisualEffectGraphs":true,"m_FxEnabled":true},"in2DMode":false,"pivot":{"x":581.5900268554688,"y":-64.40858459472656,"z":545.2286987304688},"rotation":{"x":0.17625217139720918,"y":-0.5976622700691223,"z":0.13679027557373048,"w":0.7700797915458679},"size":192.45602416992188,"orthographic":false}