{"cameraMode":{"drawMode":0,"name":"Shaded","section":"Shading Mode"},"sceneLighting":false,"audioPlay":false,"sceneViewState":{"m_AlwaysRefresh":false,"showFog":true,"showSkybox":false,"showFlares":true,"showImageEffects":true,"showParticleSystems":true,"showVisualEffectGraphs":true,"m_FxEnabled":true},"in2DMode":false,"pivot":{"x":239.20291137695313,"y":-493.0439453125,"z":579.2552490234375},"rotation":{"x":-0.4229617118835449,"y":0.40524977445602419,"z":-0.21971358358860017,"w":-0.7801316976547241},"size":577.3819580078125,"orthographic":false}